Metadata-Version: 2.1
Name: jaden-lib
Version: 0.1.0.3
Summary: A library of Jaden.
Home-page: https://gitee.com/liling
Author: Jaden Lee
Author-email: zhuoen.li@outlook.com
License: UNKNOWN
Project-URL: Bug Tracker, https://gitee.com/liling
Platform: UNKNOWN
Classifier: Programming Language :: Python :: 3
Classifier: License :: OSI Approved :: MIT License
Classifier: Operating System :: OS Independent
Requires-Python: >=3.5
